orm_alchemist/__init__.py
orm_alchemist-0.1.1.dist-info/LICENSE
orm_alchemist-0.1.1.dist-info/METADATA
orm_alchemist-0.1.1.dist-info/WHEEL
orm_alchemist-0.1.1.dist-info/RECORD
