Metadata-Version: 2.1
Name: orm-alchemist
Version: 0.1.1
Summary: SQLAlchemy boilerplate for FastAPI
Home-page: https://github.com/izagood/orm-alchemist
License: MIT
Author: izagood
Author-email: ljbfif50@gmail.com
Requires-Python: >=3.9,<4.0
Classifier: License :: OSI Approved :: MIT License
Classifier: Programming Language :: Python :: 3
Classifier: Programming Language :: Python :: 3.9
Classifier: Programming Language :: Python :: 3.10
Classifier: Programming Language :: Python :: 3.11
Classifier: Programming Language :: Python :: 3.12
Project-URL: Repository, https://github.com/izagood/orm-alchemist
